Workbook

Sheet Rent vs Buy Calculator
B2: RENT VS BUY CALCULATOR
B3: Compare renting vs buying. Enter your numbers in the teal cells.
B5: PURCHASE DETAILS | F5: RESULTS
B6: Home Purchase Price | C6: 400000 | F6: Loan Amount | G6: =C6*(1-C7)
B7: Down Payment % | C7: 0.2 | F7: Monthly P&I | G7: =IF(C8>0,PMT(C8/12,C9*12,-G6),0)
B8: Mortgage Interest Rate | C8: 0.065 | F8: Down Payment | G8: =C6*C7
B9: Mortgage Term (years) | C9: 30 | F9: Closing Costs | G9: =C6*C20
B11: RENTING | F11: Monthly Tax+Ins+HOA+Maint | G11: =C6*C16/12+C17/12+C18+C6*C19/12
B12: Monthly Rent | C12: 2000 | F12: Total Monthly (Buy) | G12: =G7+G11
B13: Annual Rent Increase % | C13: 0.03
F14: VERDICT
B15: OWNERSHIP COSTS | F15: ='Year-by-Year'!K40
B16: Property Tax Rate % | C16: 0.012
B17: Home Insurance ($/year) | C17: 1500
B18: HOA Fees ($/month) | C18: 0
B19: Maintenance % of value/year | C19: 0.01
B20: Closing Costs % | C20: 0.03
F21: MONTHLY COMPARISON
B22: ASSUMPTIONS | F22: Buy (total) | G22: =G12
B23: Home Appreciation Rate % | C23: 0.035 | F23: Rent (year 1) | G23: =C12
B24: Investment Return % | C24: 0.07 | D24: opportunity cost
B25: Income Tax Bracket % | C25: 0.24 | D25: for mortgage deduction
B26: Years to Compare | C26: 10

Sheet Year-by-Year
B2: YEAR-BY-YEAR COMPARISON
B3: 30-year projection. Buyer equity vs Renter investments.
B5: Year | C5: Home Value | D5: Mortgage Bal | E5: Buyer Equity | F5: Cum Cost Buy | G5: Cum Cost Rent | H5: Renter Inv | I5: Buy Wins? | J5: Verdict
B6: 1 | C6: ='Rent vs Buy Calculator'!C6*(1+'Rent vs Buy Calculator'!C23)^1 | D6: =MAX(0,FV('Rent vs Buy Calculator'!C8/12,(0+1)*12,-'Rent vs Buy Calculator'!G7,'Rent vs Buy Calculator'!G6)) | E6: =C6-D6 | F6: ='Rent vs Buy Calculator'!G8+'Rent vs Buy Calculator'!G9+'Rent vs Buy Calculator'!G7*12+'Rent vs Buy Calculator'!C6*'Rent vs Buy Calculator'!C16+'Rent vs Buy Calculator'!C17+'Rent vs Buy Calculator'!C18*12+'Rent vs Buy Calculator'!C6*'Rent vs Buy Calculator'!C19-CUMIPMT('Rent vs Buy Calculator'!C8/12,'Rent vs Buy Calculator'!C9*12,'Rent vs Buy Calculator'!G6,1,12,0)*'Rent vs Buy Calculator'!C25 | G6: ='Rent vs Buy Calculator'!C12*12 | H6: ='Rent vs Buy Calculator'!G8*(1+'Rent vs Buy Calculator'!C24)^1 | I6: =IF(E6>H6,1,0) | J6: =IF(E6>H6,"Buy wins","Rent wins")
B7: 2 | C7: ='Rent vs Buy Calculator'!C6*(1+'Rent vs Buy Calculator'!C23)^2 | D7: =MAX(0,FV('Rent vs Buy Calculator'!C8/12,(1+1)*12,-'Rent vs Buy Calculator'!G7,'Rent vs Buy Calculator'!G6)) | E7: =C7-D7 | F7: =F6+'Rent vs Buy Calculator'!G7*12+'Rent vs Buy Calculator'!C6*(1+'Rent vs Buy Calculator'!C23)^1*'Rent vs Buy Calculator'!C16+'Rent vs Buy Calculator'!C17+'Rent vs Buy Calculator'!C18*12+'Rent vs Buy Calculator'!C6*(1+'Rent vs Buy Calculator'!C23)^1*'Rent vs Buy Calculator'!C19-CUMIPMT('Rent vs Buy Calculator'!C8/12,'Rent vs Buy Calculator'!C9*12,'Rent vs Buy Calculator'!G6,13,24,0)*'Rent vs Buy Calculator'!C25 | G7: =G6+'Rent vs Buy Calculator'!C12*12*(1+'Rent vs Buy Calculator'!C13)^1 | H7: ='Rent vs Buy Calculator'!G8*(1+'Rent vs Buy Calculator'!C24)^2 | I7: =IF(E7>H7,1,0) | J7: =IF(E7>H7,"Buy wins","Rent wins")
B8: 3 | C8: ='Rent vs Buy Calculator'!C6*(1+'Rent vs Buy Calculator'!C23)^3 | D8: =MAX(0,FV('Rent vs Buy Calculator'!C8/12,(2+1)*12,-'Rent vs Buy Calculator'!G7,'Rent vs Buy Calculator'!G6)) | E8: =C8-D8 | F8: =F7+'Rent vs Buy Calculator'!G7*12+'Rent vs Buy Calculator'!C6*(1+'Rent vs Buy Calculator'!C23)^2*'Rent vs Buy Calculator'!C16+'Rent vs Buy Calculator'!C17+'Rent vs Buy Calculator'!C18*12+'Rent vs Buy Calculator'!C6*(1+'Rent vs Buy Calculator'!C23)^2*'Rent vs Buy Calculator'!C19-CUMIPMT('Rent vs Buy Calculator'!C8/12,'Rent vs Buy Calculator'!C9*12,'Rent vs Buy Calculator'!G6,25,36,0)*'Rent vs Buy Calculator'!C25 | G8: =G7+'Rent vs Buy Calculator'!C12*12*(1+'Rent vs Buy Calculator'!C13)^2 | H8: ='Rent vs Buy Calculator'!G8*(1+'Rent vs Buy Calculator'!C24)^3 | I8: =IF(E8>H8,1,0) | J8: =IF(E8>H8,"Buy wins","Rent wins")
B9: 4 | C9: ='Rent vs Buy Calculator'!C6*(1+'Rent vs Buy Calculator'!C23)^4 | D9: =MAX(0,FV('Rent vs Buy Calculator'!C8/12,(3+1)*12,-'Rent vs Buy Calculator'!G7,'Rent vs Buy Calculator'!G6)) | E9: =C9-D9 | F9: =F8+'Rent vs Buy Calculator'!G7*12+'Rent vs Buy Calculator'!C6*(1+'Rent vs Buy Calculator'!C23)^3*'Rent vs Buy Calculator'!C16+'Rent vs Buy Calculator'!C17+'Rent vs Buy Calculator'!C18*12+'Rent vs Buy Calculator'!C6*(1+'Rent vs Buy Calculator'!C23)^3*'Rent vs Buy Calculator'!C19-CUMIPMT('Rent vs Buy Calculator'!C8/12,'Rent vs Buy Calculator'!C9*12,'Rent vs Buy Calculator'!G6,37,48,0)*'Rent vs Buy Calculator'!C25 | G9: =G8+'Rent vs Buy Calculator'!C12*12*(1+'Rent vs Buy Calculator'!C13)^3 | H9: ='Rent vs Buy Calculator'!G8*(1+'Rent vs Buy Calculator'!C24)^4 | I9: =IF(E9>H9,1,0) | J9: =IF(E9>H9,"Buy wins","Rent wins")
B10: 5 | C10: ='Rent vs Buy Calculator'!C6*(1+'Rent vs Buy Calculator'!C23)^5 | D10: =MAX(0,FV('Rent vs Buy Calculator'!C8/12,(4+1)*12,-'Rent vs Buy Calculator'!G7,'Rent vs Buy Calculator'!G6)) | E10: =C10-D10 | F10: =F9+'Rent vs Buy Calculator'!G7*12+'Rent vs Buy Calculator'!C6*(1+'Rent vs Buy Calculator'!C23)^4*'Rent vs Buy Calculator'!C16+'Rent vs Buy Calculator'!C17+'Rent vs Buy Calculator'!C18*12+'Rent vs Buy Calculator'!C6*(1+'Rent vs Buy Calculator'!C23)^4*'Rent vs Buy Calculator'!C19-CUMIPMT('Rent vs Buy Calculator'!C8/12,'Rent vs Buy Calculator'!C9*12,'Rent vs Buy Calculator'!G6,49,60,0)*'Rent vs Buy Calculator'!C25 | G10: =G9+'Rent vs Buy Calculator'!C12*12*(1+'Rent vs Buy Calculator'!C13)^4 | H10: ='Rent vs Buy Calculator'!G8*(1+'Rent vs Buy Calculator'!C24)^5 | I10: =IF(E10>H10,1,0) | J10: =IF(E10>H10,"Buy wins","Rent wins")
B11: 6 | C11: ='Rent vs Buy Calculator'!C6*(1+'Rent vs Buy Calculator'!C23)^6 | D11: =MAX(0,FV('Rent vs Buy Calculator'!C8/12,(5+1)*12,-'Rent vs Buy Calculator'!G7,'Rent vs Buy Calculator'!G6)) | E11: =C11-D11 | F11: =F10+'Rent vs Buy Calculator'!G7*12+'Rent vs Buy Calculator'!C6*(1+'Rent vs Buy Calculator'!C23)^5*'Rent vs Buy Calculator'!C16+'Rent vs Buy Calculator'!C17+'Rent vs Buy Calculator'!C18*12+'Rent vs Buy Calculator'!C6*(1+'Rent vs Buy Calculator'!C23)^5*'Rent vs Buy Calculator'!C19-CUMIPMT('Rent vs Buy Calculator'!C8/12,'Rent vs Buy Calculator'!C9*12,'Rent vs Buy Calculator'!G6,61,72,0)*'Rent vs Buy Calculator'!C25 | G11: =G10+'Rent vs Buy Calculator'!C12*12*(1+'Rent vs Buy Calculator'!C13)^5 | H11: ='Rent vs Buy Calculator'!G8*(1+'Rent vs Buy Calculator'!C24)^6 | I11: =IF(E11>H11,1,0) | J11: =IF(E11>H11,"Buy wins","Rent wins")
B12: 7 | C12: ='Rent vs Buy Calculator'!C6*(1+'Rent vs Buy Calculator'!C23)^7 | D12: =MAX(0,FV('Rent vs Buy Calculator'!C8/12,(6+1)*12,-'Rent vs Buy Calculator'!G7,'Rent vs Buy Calculator'!G6)) | E12: =C12-D12 | F12: =F11+'Rent vs Buy Calculator'!G7*12+'Rent vs Buy Calculator'!C6*(1+'Rent vs Buy Calculator'!C23)^6*'Rent vs Buy Calculator'!C16+'Rent vs Buy Calculator'!C17+'Rent vs Buy Calculator'!C18*12+'Rent vs Buy Calculator'!C6*(1+'Rent vs Buy Calculator'!C23)^6*'Rent vs Buy Calculator'!C19-CUMIPMT('Rent vs Buy Calculator'!C8/12,'Rent vs Buy Calculator'!C9*12,'Rent vs Buy Calculator'!G6,73,84,0)*'Rent vs Buy Calculator'!C25 | G12: =G11+'Rent vs Buy Calculator'!C12*12*(1+'Rent vs Buy Calculator'!C13)^6 | H12: ='Rent vs Buy Calculator'!G8*(1+'Rent vs Buy Calculator'!C24)^7 | I12: =IF(E12>H12,1,0) | J12: =IF(E12>H12,"Buy wins","Rent wins")
B13: 8 | C13: ='Rent vs Buy Calculator'!C6*(1+'Rent vs Buy Calculator'!C23)^8 | D13: =MAX(0,FV('Rent vs Buy Calculator'!C8/12,(7+1)*12,-'Rent vs Buy Calculator'!G7,'Rent vs Buy Calculator'!G6)) | E13: =C13-D13 | F13: =F12+'Rent vs Buy Calculator'!G7*12+'Rent vs Buy Calculator'!C6*(1+'Rent vs Buy Calculator'!C23)^7*'Rent vs Buy Calculator'!C16+'Rent vs Buy Calculator'!C17+'Rent vs Buy Calculator'!C18*12+'Rent vs Buy Calculator'!C6*(1+'Rent vs Buy Calculator'!C23)^7*'Rent vs Buy Calculator'!C19-CUMIPMT('Rent vs Buy Calculator'!C8/12,'Rent vs Buy Calculator'!C9*12,'Rent vs Buy Calculator'!G6,85,96,0)*'Rent vs Buy Calculator'!C25 | G13: =G12+'Rent vs Buy Calculator'!C12*12*(1+'Rent vs Buy Calculator'!C13)^7 | H13: ='Rent vs Buy Calculator'!G8*(1+'Rent vs Buy Calculator'!C24)^8 | I13: =IF(E13>H13,1,0) | J13: =IF(E13>H13,"Buy wins","Rent wins")
B14: 9 | C14: ='Rent vs Buy Calculator'!C6*(1+'Rent vs Buy Calculator'!C23)^9 | D14: =MAX(0,FV('Rent vs Buy Calculator'!C8/12,(8+1)*12,-'Rent vs Buy Calculator'!G7,'Rent vs Buy Calculator'!G6)) | E14: =C14-D14 | F14: =F13+'Rent vs Buy Calculator'!G7*12+'Rent vs Buy Calculator'!C6*(1+'Rent vs Buy Calculator'!C23)^8*'Rent vs Buy Calculator'!C16+'Rent vs Buy Calculator'!C17+'Rent vs Buy Calculator'!C18*12+'Rent vs Buy Calculator'!C6*(1+'Rent vs Buy Calculator'!C23)^8*'Rent vs Buy Calculator'!C19-CUMIPMT('Rent vs Buy Calculator'!C8/12,'Rent vs Buy Calculator'!C9*12,'Rent vs Buy Calculator'!G6,97,108,0)*'Rent vs Buy Calculator'!C25 | G14: =G13+'Rent vs Buy Calculator'!C12*12*(1+'Rent vs Buy Calculator'!C13)^8 | H14: ='Rent vs Buy Calculator'!G8*(1+'Rent vs Buy Calculator'!C24)^9 | I14: =IF(E14>H14,1,0) | J14: =IF(E14>H14,"Buy wins","Rent wins")
B15: 10 | C15: ='Rent vs Buy Calculator'!C6*(1+'Rent vs Buy Calculator'!C23)^10 | D15: =MAX(0,FV('Rent vs Buy Calculator'!C8/12,(9+1)*12,-'Rent vs Buy Calculator'!G7,'Rent vs Buy Calculator'!G6)) | E15: =C15-D15 | F15: =F14+'Rent vs Buy Calculator'!G7*12+'Rent vs Buy Calculator'!C6*(1+'Rent vs Buy Calculator'!C23)^9*'Rent vs Buy Calculator'!C16+'Rent vs Buy Calculator'!C17+'Rent vs Buy Calculator'!C18*12+'Rent vs Buy Calculator'!C6*(1+'Rent vs Buy Calculator'!C23)^9*'Rent vs Buy Calculator'!C19-CUMIPMT('Rent vs Buy Calculator'!C8/12,'Rent vs Buy Calculator'!C9*12,'Rent vs Buy Calculator'!G6,109,120,0)*'Rent vs Buy Calculator'!C25 | G15: =G14+'Rent vs Buy Calculator'!C12*12*(1+'Rent vs Buy Calculator'!C13)^9 | H15: ='Rent vs Buy Calculator'!G8*(1+'Rent vs Buy Calculator'!C24)^10 | I15: =IF(E15>H15,1,0) | J15: =IF(E15>H15,"Buy wins","Rent wins")
B16: 11 | C16: ='Rent vs Buy Calculator'!C6*(1+'Rent vs Buy Calculator'!C23)^11 | D16: =MAX(0,FV('Rent vs Buy Calculator'!C8/12,(10+1)*12,-'Rent vs Buy Calculator'!G7,'Rent vs Buy Calculator'!G6)) | E16: =C16-D16 | F16: =F15+'Rent vs Buy Calculator'!G7*12+'Rent vs Buy Calculator'!C6*(1+'Rent vs Buy Calculator'!C23)^10*'Rent vs Buy Calculator'!C16+'Rent vs Buy Calculator'!C17+'Rent vs Buy Calculator'!C18*12+'Rent vs Buy Calculator'!C6*(1+'Rent vs Buy Calculator'!C23)^10*'Rent vs Buy Calculator'!C19-CUMIPMT('Rent vs Buy Calculator'!C8/12,'Rent vs Buy Calculator'!C9*12,'Rent vs Buy Calculator'!G6,121,132,0)*'Rent vs Buy Calculator'!C25 | G16: =G15+'Rent vs Buy Calculator'!C12*12*(1+'Rent vs Buy Calculator'!C13)^10 | H16: ='Rent vs Buy Calculator'!G8*(1+'Rent vs Buy Calculator'!C24)^11 | I16: =IF(E16>H16,1,0) | J16: =IF(E16>H16,"Buy wins","Rent wins")
B17: 12 | C17: ='Rent vs Buy Calculator'!C6*(1+'Rent vs Buy Calculator'!C23)^12 | D17: =MAX(0,FV('Rent vs Buy Calculator'!C8/12,(11+1)*12,-'Rent vs Buy Calculator'!G7,'Rent vs Buy Calculator'!G6)) | E17: =C17-D17 | F17: =F16+'Rent vs Buy Calculator'!G7*12+'Rent vs Buy Calculator'!C6*(1+'Rent vs Buy Calculator'!C23)^11*'Rent vs Buy Calculator'!C16+'Rent vs Buy Calculator'!C17+'Rent vs Buy Calculator'!C18*12+'Rent vs Buy Calculator'!C6*(1+'Rent vs Buy Calculator'!C23)^11*'Rent vs Buy Calculator'!C19-CUMIPMT('Rent vs Buy Calculator'!C8/12,'Rent vs Buy Calculator'!C9*12,'Rent vs Buy Calculator'!G6,133,144,0)*'Rent vs Buy Calculator'!C25 | G17: =G16+'Rent vs Buy Calculator'!C12*12*(1+'Rent vs Buy Calculator'!C13)^11 | H17: ='Rent vs Buy Calculator'!G8*(1+'Rent vs Buy Calculator'!C24)^12 | I17: =IF(E17>H17,1,0) | J17: =IF(E17>H17,"Buy wins","Rent wins")
B18: 13 | C18: ='Rent vs Buy Calculator'!C6*(1+'Rent vs Buy Calculator'!C23)^13 | D18: =MAX(0,FV('Rent vs Buy Calculator'!C8/12,(12+1)*12,-'Rent vs Buy Calculator'!G7,'Rent vs Buy Calculator'!G6)) | E18: =C18-D18 | F18: =F17+'Rent vs Buy Calculator'!G7*12+'Rent vs Buy Calculator'!C6*(1+'Rent vs Buy Calculator'!C23)^12*'Rent vs Buy Calculator'!C16+'Rent vs Buy Calculator'!C17+'Rent vs Buy Calculator'!C18*12+'Rent vs Buy Calculator'!C6*(1+'Rent vs Buy Calculator'!C23)^12*'Rent vs Buy Calculator'!C19-CUMIPMT('Rent vs Buy Calculator'!C8/12,'Rent vs Buy Calculator'!C9*12,'Rent vs Buy Calculator'!G6,145,156,0)*'Rent vs Buy Calculator'!C25 | G18: =G17+'Rent vs Buy Calculator'!C12*12*(1+'Rent vs Buy Calculator'!C13)^12 | H18: ='Rent vs Buy Calculator'!G8*(1+'Rent vs Buy Calculator'!C24)^13 | I18: =IF(E18>H18,1,0) | J18: =IF(E18>H18,"Buy wins","Rent wins")
B19: 14 | C19: ='Rent vs Buy Calculator'!C6*(1+'Rent vs Buy Calculator'!C23)^14 | D19: =MAX(0,FV('Rent vs Buy Calculator'!C8/12,(13+1)*12,-'Rent vs Buy Calculator'!G7,'Rent vs Buy Calculator'!G6)) | E19: =C19-D19 | F19: =F18+'Rent vs Buy Calculator'!G7*12+'Rent vs Buy Calculator'!C6*(1+'Rent vs Buy Calculator'!C23)^13*'Rent vs Buy Calculator'!C16+'Rent vs Buy Calculator'!C17+'Rent vs Buy Calculator'!C18*12+'Rent vs Buy Calculator'!C6*(1+'Rent vs Buy Calculator'!C23)^13*'Rent vs Buy Calculator'!C19-CUMIPMT('Rent vs Buy Calculator'!C8/12,'Rent vs Buy Calculator'!C9*12,'Rent vs Buy Calculator'!G6,157,168,0)*'Rent vs Buy Calculator'!C25 | G19: =G18+'Rent vs Buy Calculator'!C12*12*(1+'Rent vs Buy Calculator'!C13)^13 | H19: ='Rent vs Buy Calculator'!G8*(1+'Rent vs Buy Calculator'!C24)^14 | I19: =IF(E19>H19,1,0) | J19: =IF(E19>H19,"Buy wins","Rent wins")
B20: 15 | C20: ='Rent vs Buy Calculator'!C6*(1+'Rent vs Buy Calculator'!C23)^15 | D20: =MAX(0,FV('Rent vs Buy Calculator'!C8/12,(14+1)*12,-'Rent vs Buy Calculator'!G7,'Rent vs Buy Calculator'!G6)) | E20: =C20-D20 | F20: =F19+'Rent vs Buy Calculator'!G7*12+'Rent vs Buy Calculator'!C6*(1+'Rent vs Buy Calculator'!C23)^14*'Rent vs Buy Calculator'!C16+'Rent vs Buy Calculator'!C17+'Rent vs Buy Calculator'!C18*12+'Rent vs Buy Calculator'!C6*(1+'Rent vs Buy Calculator'!C23)^14*'Rent vs Buy Calculator'!C19-CUMIPMT('Rent vs Buy Calculator'!C8/12,'Rent vs Buy Calculator'!C9*12,'Rent vs Buy Calculator'!G6,169,180,0)*'Rent vs Buy Calculator'!C25 | G20: =G19+'Rent vs Buy Calculator'!C12*12*(1+'Rent vs Buy Calculator'!C13)^14 | H20: ='Rent vs Buy Calculator'!G8*(1+'Rent vs Buy Calculator'!C24)^15 | I20: =IF(E20>H20,1,0) | J20: =IF(E20>H20,"Buy wins","Rent wins")
B21: 16 | C21: ='Rent vs Buy Calculator'!C6*(1+'Rent vs Buy Calculator'!C23)^16 | D21: =MAX(0,FV('Rent vs Buy Calculator'!C8/12,(15+1)*12,-'Rent vs Buy Calculator'!G7,'Rent vs Buy Calculator'!G6)) | E21: =C21-D21 | F21: =F20+'Rent vs Buy Calculator'!G7*12+'Rent vs Buy Calculator'!C6*(1+'Rent vs Buy Calculator'!C23)^15*'Rent vs Buy Calculator'!C16+'Rent vs Buy Calculator'!C17+'Rent vs Buy Calculator'!C18*12+'Rent vs Buy Calculator'!C6*(1+'Rent vs Buy Calculator'!C23)^15*'Rent vs Buy Calculator'!C19-CUMIPMT('Rent vs Buy Calculator'!C8/12,'Rent vs Buy Calculator'!C9*12,'Rent vs Buy Calculator'!G6,181,192,0)*'Rent vs Buy Calculator'!C25 | G21: =G20+'Rent vs Buy Calculator'!C12*12*(1+'Rent vs Buy Calculator'!C13)^15 | H21: ='Rent vs Buy Calculator'!G8*(1+'Rent vs Buy Calculator'!C24)^16 | I21: =IF(E21>H21,1,0) | J21: =IF(E21>H21,"Buy wins","Rent wins")
B22: 17 | C22: ='Rent vs Buy Calculator'!C6*(1+'Rent vs Buy Calculator'!C23)^17 | D22: =MAX(0,FV('Rent vs Buy Calculator'!C8/12,(16+1)*12,-'Rent vs Buy Calculator'!G7,'Rent vs Buy Calculator'!G6)) | E22: =C22-D22 | F22: =F21+'Rent vs Buy Calculator'!G7*12+'Rent vs Buy Calculator'!C6*(1+'Rent vs Buy Calculator'!C23)^16*'Rent vs Buy Calculator'!C16+'Rent vs Buy Calculator'!C17+'Rent vs Buy Calculator'!C18*12+'Rent vs Buy Calculator'!C6*(1+'Rent vs Buy Calculator'!C23)^16*'Rent vs Buy Calculator'!C19-CUMIPMT('Rent vs Buy Calculator'!C8/12,'Rent vs Buy Calculator'!C9*12,'Rent vs Buy Calculator'!G6,193,204,0)*'Rent vs Buy Calculator'!C25 | G22: =G21+'Rent vs Buy Calculator'!C12*12*(1+'Rent vs Buy Calculator'!C13)^16 | H22: ='Rent vs Buy Calculator'!G8*(1+'Rent vs Buy Calculator'!C24)^17 | I22: =IF(E22>H22,1,0) | J22: =IF(E22>H22,"Buy wins","Rent wins")
B23: 18 | C23: ='Rent vs Buy Calculator'!C6*(1+'Rent vs Buy Calculator'!C23)^18 | D23: =MAX(0,FV('Rent vs Buy Calculator'!C8/12,(17+1)*12,-'Rent vs Buy Calculator'!G7,'Rent vs Buy Calculator'!G6)) | E23: =C23-D23 | F23: =F22+'Rent vs Buy Calculator'!G7*12+'Rent vs Buy Calculator'!C6*(1+'Rent vs Buy Calculator'!C23)^17*'Rent vs Buy Calculator'!C16+'Rent vs Buy Calculator'!C17+'Rent vs Buy Calculator'!C18*12+'Rent vs Buy Calculator'!C6*(1+'Rent vs Buy Calculator'!C23)^17*'Rent vs Buy Calculator'!C19-CUMIPMT('Rent vs Buy Calculator'!C8/12,'Rent vs Buy Calculator'!C9*12,'Rent vs Buy Calculator'!G6,205,216,0)*'Rent vs Buy Calculator'!C25 | G23: =G22+'Rent vs Buy Calculator'!C12*12*(1+'Rent vs Buy Calculator'!C13)^17 | H23: ='Rent vs Buy Calculator'!G8*(1+'Rent vs Buy Calculator'!C24)^18 | I23: =IF(E23>H23,1,0) | J23: =IF(E23>H23,"Buy wins","Rent wins")
B24: 19 | C24: ='Rent vs Buy Calculator'!C6*(1+'Rent vs Buy Calculator'!C23)^19 | D24: =MAX(0,FV('Rent vs Buy Calculator'!C8/12,(18+1)*12,-'Rent vs Buy Calculator'!G7,'Rent vs Buy Calculator'!G6)) | E24: =C24-D24 | F24: =F23+'Rent vs Buy Calculator'!G7*12+'Rent vs Buy Calculator'!C6*(1+'Rent vs Buy Calculator'!C23)^18*'Rent vs Buy Calculator'!C16+'Rent vs Buy Calculator'!C17+'Rent vs Buy Calculator'!C18*12+'Rent vs Buy Calculator'!C6*(1+'Rent vs Buy Calculator'!C23)^18*'Rent vs Buy Calculator'!C19-CUMIPMT('Rent vs Buy Calculator'!C8/12,'Rent vs Buy Calculator'!C9*12,'Rent vs Buy Calculator'!G6,217,228,0)*'Rent vs Buy Calculator'!C25 | G24: =G23+'Rent vs Buy Calculator'!C12*12*(1+'Rent vs Buy Calculator'!C13)^18 | H24: ='Rent vs Buy Calculator'!G8*(1+'Rent vs Buy Calculator'!C24)^19 | I24: =IF(E24>H24,1,0) | J24: =IF(E24>H24,"Buy wins","Rent wins")
B25: 20 | C25: ='Rent vs Buy Calculator'!C6*(1+'Rent vs Buy Calculator'!C23)^20 | D25: =MAX(0,FV('Rent vs Buy Calculator'!C8/12,(19+1)*12,-'Rent vs Buy Calculator'!G7,'Rent vs Buy Calculator'!G6)) | E25: =C25-D25 | F25: =F24+'Rent vs Buy Calculator'!G7*12+'Rent vs Buy Calculator'!C6*(1+'Rent vs Buy Calculator'!C23)^19*'Rent vs Buy Calculator'!C16+'Rent vs Buy Calculator'!C17+'Rent vs Buy Calculator'!C18*12+'Rent vs Buy Calculator'!C6*(1+'Rent vs Buy Calculator'!C23)^19*'Rent vs Buy Calculator'!C19-CUMIPMT('Rent vs Buy Calculator'!C8/12,'Rent vs Buy Calculator'!C9*12,'Rent vs Buy Calculator'!G6,229,240,0)*'Rent vs Buy Calculator'!C25 | G25: =G24+'Rent vs Buy Calculator'!C12*12*(1+'Rent vs Buy Calculator'!C13)^19 | H25: ='Rent vs Buy Calculator'!G8*(1+'Rent vs Buy Calculator'!C24)^20 | I25: =IF(E25>H25,1,0) | J25: =IF(E25>H25,"Buy wins","Rent wins")
B26: 21 | C26: ='Rent vs Buy Calculator'!C6*(1+'Rent vs Buy Calculator'!C23)^21 | D26: =MAX(0,FV('Rent vs Buy Calculator'!C8/12,(20+1)*12,-'Rent vs Buy Calculator'!G7,'Rent vs Buy Calculator'!G6)) | E26: =C26-D26 | F26: =F25+'Rent vs Buy Calculator'!G7*12+'Rent vs Buy Calculator'!C6*(1+'Rent vs Buy Calculator'!C23)^20*'Rent vs Buy Calculator'!C16+'Rent vs Buy Calculator'!C17+'Rent vs Buy Calculator'!C18*12+'Rent vs Buy Calculator'!C6*(1+'Rent vs Buy Calculator'!C23)^20*'Rent vs Buy Calculator'!C19-CUMIPMT('Rent vs Buy Calculator'!C8/12,'Rent vs Buy Calculator'!C9*12,'Rent vs Buy Calculator'!G6,241,252,0)*'Rent vs Buy Calculator'!C25 | G26: =G25+'Rent vs Buy Calculator'!C12*12*(1+'Rent vs Buy Calculator'!C13)^20 | H26: ='Rent vs Buy Calculator'!G8*(1+'Rent vs Buy Calculator'!C24)^21 | I26: =IF(E26>H26,1,0) | J26: =IF(E26>H26,"Buy wins","Rent wins")
B27: 22 | C27: ='Rent vs Buy Calculator'!C6*(1+'Rent vs Buy Calculator'!C23)^22 | D27: =MAX(0,FV('Rent vs Buy Calculator'!C8/12,(21+1)*12,-'Rent vs Buy Calculator'!G7,'Rent vs Buy Calculator'!G6)) | E27: =C27-D27 | F27: =F26+'Rent vs Buy Calculator'!G7*12+'Rent vs Buy Calculator'!C6*(1+'Rent vs Buy Calculator'!C23)^21*'Rent vs Buy Calculator'!C16+'Rent vs Buy Calculator'!C17+'Rent vs Buy Calculator'!C18*12+'Rent vs Buy Calculator'!C6*(1+'Rent vs Buy Calculator'!C23)^21*'Rent vs Buy Calculator'!C19-CUMIPMT('Rent vs Buy Calculator'!C8/12,'Rent vs Buy Calculator'!C9*12,'Rent vs Buy Calculator'!G6,253,264,0)*'Rent vs Buy Calculator'!C25 | G27: =G26+'Rent vs Buy Calculator'!C12*12*(1+'Rent vs Buy Calculator'!C13)^21 | H27: ='Rent vs Buy Calculator'!G8*(1+'Rent vs Buy Calculator'!C24)^22 | I27: =IF(E27>H27,1,0) | J27: =IF(E27>H27,"Buy wins","Rent wins")
B28: 23 | C28: ='Rent vs Buy Calculator'!C6*(1+'Rent vs Buy Calculator'!C23)^23 | D28: =MAX(0,FV('Rent vs Buy Calculator'!C8/12,(22+1)*12,-'Rent vs Buy Calculator'!G7,'Rent vs Buy Calculator'!G6)) | E28: =C28-D28 | F28: =F27+'Rent vs Buy Calculator'!G7*12+'Rent vs Buy Calculator'!C6*(1+'Rent vs Buy Calculator'!C23)^22*'Rent vs Buy Calculator'!C16+'Rent vs Buy Calculator'!C17+'Rent vs Buy Calculator'!C18*12+'Rent vs Buy Calculator'!C6*(1+'Rent vs Buy Calculator'!C23)^22*'Rent vs Buy Calculator'!C19-CUMIPMT('Rent vs Buy Calculator'!C8/12,'Rent vs Buy Calculator'!C9*12,'Rent vs Buy Calculator'!G6,265,276,0)*'Rent vs Buy Calculator'!C25 | G28: =G27+'Rent vs Buy Calculator'!C12*12*(1+'Rent vs Buy Calculator'!C13)^22 | H28: ='Rent vs Buy Calculator'!G8*(1+'Rent vs Buy Calculator'!C24)^23 | I28: =IF(E28>H28,1,0) | J28: =IF(E28>H28,"Buy wins","Rent wins")
B29: 24 | C29: ='Rent vs Buy Calculator'!C6*(1+'Rent vs Buy Calculator'!C23)^24 | D29: =MAX(0,FV('Rent vs Buy Calculator'!C8/12,(23+1)*12,-'Rent vs Buy Calculator'!G7,'Rent vs Buy Calculator'!G6)) | E29: =C29-D29 | F29: =F28+'Rent vs Buy Calculator'!G7*12+'Rent vs Buy Calculator'!C6*(1+'Rent vs Buy Calculator'!C23)^23*'Rent vs Buy Calculator'!C16+'Rent vs Buy Calculator'!C17+'Rent vs Buy Calculator'!C18*12+'Rent vs Buy Calculator'!C6*(1+'Rent vs Buy Calculator'!C23)^23*'Rent vs Buy Calculator'!C19-CUMIPMT('Rent vs Buy Calculator'!C8/12,'Rent vs Buy Calculator'!C9*12,'Rent vs Buy Calculator'!G6,277,288,0)*'Rent vs Buy Calculator'!C25 | G29: =G28+'Rent vs Buy Calculator'!C12*12*(1+'Rent vs Buy Calculator'!C13)^23 | H29: ='Rent vs Buy Calculator'!G8*(1+'Rent vs Buy Calculator'!C24)^24 | I29: =IF(E29>H29,1,0) | J29: =IF(E29>H29,"Buy wins","Rent wins")
B30: 25 | C30: ='Rent vs Buy Calculator'!C6*(1+'Rent vs Buy Calculator'!C23)^25 | D30: =MAX(0,FV('Rent vs Buy Calculator'!C8/12,(24+1)*12,-'Rent vs Buy Calculator'!G7,'Rent vs Buy Calculator'!G6)) | E30: =C30-D30 | F30: =F29+'Rent vs Buy Calculator'!G7*12+'Rent vs Buy Calculator'!C6*(1+'Rent vs Buy Calculator'!C23)^24*'Rent vs Buy Calculator'!C16+'Rent vs Buy Calculator'!C17+'Rent vs Buy Calculator'!C18*12+'Rent vs Buy Calculator'!C6*(1+'Rent vs Buy Calculator'!C23)^24*'Rent vs Buy Calculator'!C19-CUMIPMT('Rent vs Buy Calculator'!C8/12,'Rent vs Buy Calculator'!C9*12,'Rent vs Buy Calculator'!G6,289,300,0)*'Rent vs Buy Calculator'!C25 | G30: =G29+'Rent vs Buy Calculator'!C12*12*(1+'Rent vs Buy Calculator'!C13)^24 | H30: ='Rent vs Buy Calculator'!G8*(1+'Rent vs Buy Calculator'!C24)^25 | I30: =IF(E30>H30,1,0) | J30: =IF(E30>H30,"Buy wins","Rent wins")
B31: 26 | C31: ='Rent vs Buy Calculator'!C6*(1+'Rent vs Buy Calculator'!C23)^26 | D31: =MAX(0,FV('Rent vs Buy Calculator'!C8/12,(25+1)*12,-'Rent vs Buy Calculator'!G7,'Rent vs Buy Calculator'!G6)) | E31: =C31-D31 | F31: =F30+'Rent vs Buy Calculator'!G7*12+'Rent vs Buy Calculator'!C6*(1+'Rent vs Buy Calculator'!C23)^25*'Rent vs Buy Calculator'!C16+'Rent vs Buy Calculator'!C17+'Rent vs Buy Calculator'!C18*12+'Rent vs Buy Calculator'!C6*(1+'Rent vs Buy Calculator'!C23)^25*'Rent vs Buy Calculator'!C19-CUMIPMT('Rent vs Buy Calculator'!C8/12,'Rent vs Buy Calculator'!C9*12,'Rent vs Buy Calculator'!G6,301,312,0)*'Rent vs Buy Calculator'!C25 | G31: =G30+'Rent vs Buy Calculator'!C12*12*(1+'Rent vs Buy Calculator'!C13)^25 | H31: ='Rent vs Buy Calculator'!G8*(1+'Rent vs Buy Calculator'!C24)^26 | I31: =IF(E31>H31,1,0) | J31: =IF(E31>H31,"Buy wins","Rent wins")
B32: 27 | C32: ='Rent vs Buy Calculator'!C6*(1+'Rent vs Buy Calculator'!C23)^27 | D32: =MAX(0,FV('Rent vs Buy Calculator'!C8/12,(26+1)*12,-'Rent vs Buy Calculator'!G7,'Rent vs Buy Calculator'!G6)) | E32: =C32-D32 | F32: =F31+'Rent vs Buy Calculator'!G7*12+'Rent vs Buy Calculator'!C6*(1+'Rent vs Buy Calculator'!C23)^26*'Rent vs Buy Calculator'!C16+'Rent vs Buy Calculator'!C17+'Rent vs Buy Calculator'!C18*12+'Rent vs Buy Calculator'!C6*(1+'Rent vs Buy Calculator'!C23)^26*'Rent vs Buy Calculator'!C19-CUMIPMT('Rent vs Buy Calculator'!C8/12,'Rent vs Buy Calculator'!C9*12,'Rent vs Buy Calculator'!G6,313,324,0)*'Rent vs Buy Calculator'!C25 | G32: =G31+'Rent vs Buy Calculator'!C12*12*(1+'Rent vs Buy Calculator'!C13)^26 | H32: ='Rent vs Buy Calculator'!G8*(1+'Rent vs Buy Calculator'!C24)^27 | I32: =IF(E32>H32,1,0) | J32: =IF(E32>H32,"Buy wins","Rent wins")
B33: 28 | C33: ='Rent vs Buy Calculator'!C6*(1+'Rent vs Buy Calculator'!C23)^28 | D33: =MAX(0,FV('Rent vs Buy Calculator'!C8/12,(27+1)*12,-'Rent vs Buy Calculator'!G7,'Rent vs Buy Calculator'!G6)) | E33: =C33-D33 | F33: =F32+'Rent vs Buy Calculator'!G7*12+'Rent vs Buy Calculator'!C6*(1+'Rent vs Buy Calculator'!C23)^27*'Rent vs Buy Calculator'!C16+'Rent vs Buy Calculator'!C17+'Rent vs Buy Calculator'!C18*12+'Rent vs Buy Calculator'!C6*(1+'Rent vs Buy Calculator'!C23)^27*'Rent vs Buy Calculator'!C19-CUMIPMT('Rent vs Buy Calculator'!C8/12,'Rent vs Buy Calculator'!C9*12,'Rent vs Buy Calculator'!G6,325,336,0)*'Rent vs Buy Calculator'!C25 | G33: =G32+'Rent vs Buy Calculator'!C12*12*(1+'Rent vs Buy Calculator'!C13)^27 | H33: ='Rent vs Buy Calculator'!G8*(1+'Rent vs Buy Calculator'!C24)^28 | I33: =IF(E33>H33,1,0) | J33: =IF(E33>H33,"Buy wins","Rent wins")
B34: 29 | C34: ='Rent vs Buy Calculator'!C6*(1+'Rent vs Buy Calculator'!C23)^29 | D34: =MAX(0,FV('Rent vs Buy Calculator'!C8/12,(28+1)*12,-'Rent vs Buy Calculator'!G7,'Rent vs Buy Calculator'!G6)) | E34: =C34-D34 | F34: =F33+'Rent vs Buy Calculator'!G7*12+'Rent vs Buy Calculator'!C6*(1+'Rent vs Buy Calculator'!C23)^28*'Rent vs Buy Calculator'!C16+'Rent vs Buy Calculator'!C17+'Rent vs Buy Calculator'!C18*12+'Rent vs Buy Calculator'!C6*(1+'Rent vs Buy Calculator'!C23)^28*'Rent vs Buy Calculator'!C19-CUMIPMT('Rent vs Buy Calculator'!C8/12,'Rent vs Buy Calculator'!C9*12,'Rent vs Buy Calculator'!G6,337,348,0)*'Rent vs Buy Calculator'!C25 | G34: =G33+'Rent vs Buy Calculator'!C12*12*(1+'Rent vs Buy Calculator'!C13)^28 | H34: ='Rent vs Buy Calculator'!G8*(1+'Rent vs Buy Calculator'!C24)^29 | I34: =IF(E34>H34,1,0) | J34: =IF(E34>H34,"Buy wins","Rent wins")
B35: 30 | C35: ='Rent vs Buy Calculator'!C6*(1+'Rent vs Buy Calculator'!C23)^30 | D35: =MAX(0,FV('Rent vs Buy Calculator'!C8/12,(29+1)*12,-'Rent vs Buy Calculator'!G7,'Rent vs Buy Calculator'!G6)) | E35: =C35-D35 | F35: =F34+'Rent vs Buy Calculator'!G7*12+'Rent vs Buy Calculator'!C6*(1+'Rent vs Buy Calculator'!C23)^29*'Rent vs Buy Calculator'!C16+'Rent vs Buy Calculator'!C17+'Rent vs Buy Calculator'!C18*12+'Rent vs Buy Calculator'!C6*(1+'Rent vs Buy Calculator'!C23)^29*'Rent vs Buy Calculator'!C19-CUMIPMT('Rent vs Buy Calculator'!C8/12,'Rent vs Buy Calculator'!C9*12,'Rent vs Buy Calculator'!G6,349,360,0)*'Rent vs Buy Calculator'!C25 | G35: =G34+'Rent vs Buy Calculator'!C12*12*(1+'Rent vs Buy Calculator'!C13)^29 | H35: ='Rent vs Buy Calculator'!G8*(1+'Rent vs Buy Calculator'!C24)^30 | I35: =IF(E35>H35,1,0) | J35: =IF(E35>H35,"Buy wins","Rent wins")
B40: Summary | K40: =IF(COUNTIF(I6:I35,1)>0,"Buy better after year "&MATCH(1,I6:I35,0)&"","Renting better for "&'Rent vs Buy Calculator'!C26&" years")

Sheet What-If Scenarios
B2: WHAT-IF SCENARIOS
B3: Compare current market vs optimistic vs conservative assumptions.
B5: Parameter | C5: Current Market | E5: Optimistic | G5: Conservative
B6: Mortgage Rate | C6: ='Rent vs Buy Calculator'!C8 | E6: 0.055 | G6: 0.075
B7: Rent Increase | C7: ='Rent vs Buy Calculator'!C13 | E7: 0.02 | G7: 0.05
B8: Home Appreciation | C8: ='Rent vs Buy Calculator'!C23 | E8: 0.05 | G8: 0.02
B9: Investment Return | C9: ='Rent vs Buy Calculator'!C24 | E9: 0.08 | G9: 0.05
B11: RESULTS AT YEAR 10
B12: Buyer Equity (Yr 10) | C12: ='Rent vs Buy Calculator'!C6*(1+'Rent vs Buy Calculator'!C23)^10-FV('Rent vs Buy Calculator'!C8/12,120,-'Rent vs Buy Calculator'!G7,'Rent vs Buy Calculator'!G6) | E12: ='Rent vs Buy Calculator'!C6*(1+E8)^10-FV(E6/12,120,-'Rent vs Buy Calculator'!G7,'Rent vs Buy Calculator'!G6) | G12: ='Rent vs Buy Calculator'!C6*(1+G8)^10-FV(G6/12,120,-'Rent vs Buy Calculator'!G7,'Rent vs Buy Calculator'!G6)
B13: Renter Investments (Yr 10) | C13: ='Rent vs Buy Calculator'!G8*(1+'Rent vs Buy Calculator'!C24)^10 | E13: ='Rent vs Buy Calculator'!G8*(1+E9)^10 | G13: ='Rent vs Buy Calculator'!G8*(1+G9)^10
B14: Winner | C14: =IF(C12>C13,"Buy","Rent") | E14: =IF(E12>E13,"Buy","Rent") | G14: =IF(G12>G13,"Buy","Rent")

Sheet How To Use
A1: HOW TO USE THE RENT VS BUY CALCULATOR
B4: QUICK START
B5: 1. Open the 'Rent vs Buy Calculator' tab and enter your numbers in the TEAL cells
B6: 2. Results appear on the right: monthly payment, break-even, verdict
B7: 3. Check the 'Year-by-Year' tab for the full 30-year comparison
B8: 4. Use 'What-If Scenarios' to test different market assumptions
B10: INPUT EXPLANATIONS
B11: Home Purchase Price: The total price of the home you're considering
B12: Down Payment %: Typically 20% to avoid PMI; 3-5% for FHA/conventional low-down
B13: Mortgage Rate: Current market rate for your credit profile and term
B14: Mortgage Term: 30-year = lower payment, more interest; 15-year = higher payment, less interest
B15: Monthly Rent: What you'd pay to rent a comparable home
B16: Rent Increase %: Historical average ~3%/year; adjust for your market
... B44: © 2026 ClearMetric. For educational use only. Not financial advice.
